livepopulartimes/__init__.py
livepopulartimes/crawler.py
LivePopularTimes-1.0.dist-info/LICENSE.md
LivePopularTimes-1.0.dist-info/METADATA
LivePopularTimes-1.0.dist-info/WHEEL
LivePopularTimes-1.0.dist-info/top_level.txt
LivePopularTimes-1.0.dist-info/RECORD
