Metadata-Version: 1.1
Name: LivePopularTimes
Version: 1.0
Summary: LivePopularTimes: A Google Maps scraper
Home-page: https://github.com/GrocerCheck/LivePopularTimes
Author: ihasdapie
Author-email: UNKNOWN
License: MIT
Keywords: populartimes googlemaps live,googlemaps,scraper,crawler,populartimes
Platform: UNKNOWN
Classifier: Development Status :: 4 - Beta
Classifier: Intended Audience :: Developers
Classifier: Topic :: Software Development :: Build Tools
Classifier: License :: OSI Approved :: MIT License
Classifier: Programming Language :: Python :: 3.6
Classifier: Programming Language :: Python :: 3.7
Classifier: Programming Language :: Python :: 3.8
